pathgenerator/__init__.py
pathgenerator/generator.py
pathgenerator/geometry.py
pathgenerator/pathemulator.py
pathgenerator/server.py
pathgenerator/static/playground.js
pathgenerator/static/style.css
pathgenerator/templates/playground.html
pathgenerator-0.1.2.dist-info/METADATA
pathgenerator-0.1.2.dist-info/WHEEL
pathgenerator-0.1.2.dist-info/licenses/LICENSE
pathgenerator-0.1.2.dist-info/RECORD
