Metadata-Version: 2.4
Name: pathgenerator
Version: 0.1.2
Summary: Human-like mouse path generation using PD control
Project-URL: Homepage, https://github.com/sockheadrps/Path-Generator
Author-email: Ryan Skiles <r.p.skiles@gmail.com>
License: MIT
License-File: LICENSE
Requires-Python: >=3.8
Requires-Dist: numpy>=1.20.0
Provides-Extra: server
Requires-Dist: fastapi[standard]; extra == 'server'
Requires-Dist: jinja2; extra == 'server'
Requires-Dist: uvicorn; extra == 'server'
Provides-Extra: windows
Requires-Dist: pywin32; extra == 'windows'
